fastpath.cpython-36m-x86_64-linux-gnu.so
fastpathz.cpython-36m-x86_64-linux-gnu.so
fastpath-1.9.dist-info/LICENSE
fastpath-1.9.dist-info/METADATA
fastpath-1.9.dist-info/WHEEL
fastpath-1.9.dist-info/top_level.txt
fastpath-1.9.dist-info/RECORD
