Metadata-Version: 2.1
Name: fastpath
Version: 1.9
Summary: A package for finding the best path through a network graph
Home-page: https://github.com/deprekate/fastpath
Author: Katelyn McNair
Author-email: deprekate@gmail.com
License: UNKNOWN
Platform: UNKNOWN
Classifier: Programming Language :: Python :: 3
Classifier: License :: OSI Approved :: GNU General Public License v3 or later (GPLv3+)
Classifier: Operating System :: OS Independent
Requires-Python: >3.5.2
License-File: LICENSE
